ezmath/__init__.py
ezmath-0.0.dist-info/METADATA
ezmath-0.0.dist-info/WHEEL
ezmath-0.0.dist-info/top_level.txt
ezmath-0.0.dist-info/RECORD
