Metadata-Version: 2.1
Name: ezmath
Version: 0.0
Summary: Python package for Ezmath
Home-page: UNKNOWN
Author: Prithvi Kambhampati
Author-email: kambhampati.prithvi@gmail.com
License: MIT
Platform: UNKNOWN
